RandomMandala/RandomFunctions.py
RandomMandala/RandomMandala.py
RandomMandala/__init__.py
RandomMandala-0.6.0.dist-info/LICENSE
RandomMandala-0.6.0.dist-info/METADATA
RandomMandala-0.6.0.dist-info/WHEEL
RandomMandala-0.6.0.dist-info/top_level.txt
RandomMandala-0.6.0.dist-info/RECORD
