Metadata-Version: 2.1
Name: RandomMandala
Version: 0.6.0
Summary: Generator of random mandalas.
Home-page: https://github.com/antononcube/Python-packages/tree/main/RandomMandala
Author: Anton Antonov
Author-email: antononcube@posteo.net
License: UNKNOWN
Keywords: random,mandala,random mandala,mandala diagram,image generation,generative art
Platform: UNKNOWN
Classifier: Intended Audience :: Science/Research
Classifier: Programming Language :: Python :: 3
Classifier: License :: OSI Approved :: Artistic License
Classifier: Intended Audience :: Science/Research
Classifier: Operating System :: OS Independent
Requires-Python: >=3.7
License-File: LICENSE
